{
    "models": [
        {"id": "car",               "model": "models/Car.mgcg",             "format":"MGCG"},
        {"id": "airship",           "model": "models/Airship.mgcg",         "format":"MGCG"},
        {"id": "bleachers",         "model": "models/Bleachers.mgcg",       "format":"MGCG"},
        {"id": "coin",              "model": "models/GoldCoin.mgcg",        "format":"MGCG"},
        {"id": "track",             "model": "models/Track.obj",            "format":"OBJ"},
        {"id": "barrier",           "model": "models/Barrier.obj",          "format":"OBJ"},
        {"id": "finish_line_top",   "model": "models/FinishLineTop.obj",    "format":"OBJ"},
        {"id": "finish_line_floor", "model": "models/FinishLineFloor.obj",  "format":"OBJ"},
        {"id": "small_ramps",       "model": "models/SmallRamps.obj",       "format":"OBJ"},
        {"id": "tower",             "model": "models/Tower.obj",            "format":"OBJ"},
        {"id": "banners",           "model": "models/Banners.obj",          "format":"OBJ"},
        {"id": "big_star",          "model": "models/BigStar.obj",          "format":"OBJ"},
        {"id": "rainbow",           "model": "models/Rainbow.obj",          "format":"OBJ"}
    ],
    "textures": [
        {"id": "car",               "texture": "textures/CarTexture.png"},
        {"id": "track",             "texture": "textures/RainbowTile.png"},
        {"id": "barrier",           "texture": "textures/Barrier.png"},
        {"id": "bleachers",         "texture": "textures/BleachersTexture.png"},
        {"id": "finish_line_top",   "texture": "textures/FinishLineTop.png"},
        {"id": "finish_line_floor", "texture": "textures/FinishLineFloor.png"},
        {"id": "small_ramps",       "texture": "textures/SmallRamp.png"},
        {"id": "coin",              "texture": "textures/GoldCoinTexture.png"},
        {"id": "airship",           "texture": "textures/AirshipTexture.png"},
        {"id": "banners",           "texture": "textures/Banners.png"}
    ],
    "instances": [
        {"id": "car",               "model": "car",                 "texture": "car",
         "transform": [1, 0, 0, 0,
                       0, 1, 0, 0,
                       0, 0, 1, -10,
                       0, 0, 0, 1]},
        {"id": "track",             "model": "track",               "texture": "track",
         "transform": [1, 0, 0, 0,
                       0, 1, 0, 0,
                       0, 0, 1, 0,
                       0, 0, 0, 1]},
        {"id": "barrier",           "model": "barrier",             "texture": "barrier",
         "transform": [1, 0, 0, 0,
                       0, 1, 0, 0,
                       0, 0, 1, 0,
                       0, 0, 0, 1]},
        {"id": "finish_line_top",   "model": "finish_line_top",     "texture": "finish_line_top",
         "transform": [1, 0, 0, 0,
                       0, 1, 0, 0,
                       0, 0, 1, 0,
                       0, 0, 0, 1]},
        {"id": "finish_line_floor", "model": "finish_line_floor",   "texture": "finish_line_floor",
         "transform": [1, 0, 0, 0,
                       0, 1, 0, 0,
                       0, 0, 1, 0,
                       0, 0, 0, 1]},
        {"id": "small_ramps",       "model": "small_ramps",         "texture": "small_ramps",
         "transform": [1, 0, 0, 0,
                       0, 1, 0, 0,
                       0, 0, 1, 0,
                       0, 0, 0, 1]},
        {"id": "airship",           "model": "airship",             "texture": "airship",
         "transform": [-1, 0, 0, -350,
                       0, 1, 0, 0,
                       0, 0, -1, 780,
                       0, 0, 0, 1]},
        {"id": "tower",             "model": "tower",               "texture": "barrier",
         "transform": [1, 0, 0, 0,
                       0, 1, 0, 0,
                       0, 0, 1, 0,
                       0, 0, 0, 1]},
        {"id": "banners",           "model": "banners",             "texture": "banners",
         "transform": [1, 0, 0, 0,
                       0, 1, 0, 0,
                       0, 0, 1, 0,
                       0, 0, 0, 1]},
        {"id": "big_star",          "model": "big_star",            "texture": "barrier",
         "transform": [1, 0, 0, 0,
                       0, 1, 0, 0,
                       0, 0, 1, 0,
                       0, 0, 0, 1]},
        {"id": "rainbow",           "model": "rainbow",             "texture": "track",
         "transform": [1, 0, 0, 0,
                       0, 1, 0, 0,
                       0, 0, 1, 0,
                       0, 0, 0, 1]}
        
    ]
}
